molmapnets/__init__.py
molmapnets/_nbdev.py
molmapnets/data.py
molmapnets/models.py
molmapnets/nets.py
molmapnets-0.0.1.dist-info/LICENSE
molmapnets-0.0.1.dist-info/METADATA
molmapnets-0.0.1.dist-info/WHEEL
molmapnets-0.0.1.dist-info/entry_points.txt
molmapnets-0.0.1.dist-info/top_level.txt
molmapnets-0.0.1.dist-info/RECORD
