Metadata-Version: 2.1
Name: molmapnets
Version: 0.0.1
Summary: Neural networks for MolMap generated features
Home-page: https://github.com/riversdark/molmapnets/tree/master/
Author: Olivier Ma
Author-email: olivier.ma.dq@gmail.com
License: Apache Software License 2.0
Keywords: MolMap Molecular
Platform: UNKNOWN
Classifier: Development Status :: 3 - Alpha
Classifier: Intended Audience :: Developers
Classifier: Natural Language :: English
Classifier: Programming Language :: Python :: 3.6
Classifier: Programming Language :: Python :: 3.7
Classifier: Programming Language :: Python :: 3.8
Classifier: License :: OSI Approved :: Apache Software License
Requires-Python: >=3.6
Requires-Dist: pip
Requires-Dist: packaging
Requires-Dist: numpy
Requires-Dist: scipy
Requires-Dist: pandas
Requires-Dist: scikit-learn
Requires-Dist: seaborn
Requires-Dist: torch
Requires-Dist: torchvision
Provides-Extra: dev
